adminserver
