Metadata-Version: 2.1
Name: serverlla
Version: 1.22
Summary: Configure your linux server and check for vulnerabilities with serverlla
Home-page: https://github.com/dylan14567/serverlla
Author: dylan14567
Author-email: 
License: UNKNOWN
Project-URL: Bug Tracker, https://github.com/dylan14567/serverlla/issues
Keywords: serverlla
Platform: UNKNOWN
Classifier: Programming Language :: Python :: 3
Classifier: License :: OSI Approved :: MIT License
Classifier: Operating System :: OS Independent
Requires-Python: >=3.6
License-File: LICENSE
